bmcs_cross_section/__init__.py
bmcs_cross_section/api.py
bmcs_cross_section/version.py
bmcs_cross_section/analytical_solutions/__init__.py
bmcs_cross_section/analytical_solutions/ana_frp_bending.py
bmcs_cross_section/crack_bridge/__init__.py
bmcs_cross_section/cs_design/__init__.py
bmcs_cross_section/cs_design/cs_design.py
bmcs_cross_section/cs_design/cs_layout.py
bmcs_cross_section/cs_design/cs_layout_dict.py
bmcs_cross_section/cs_design/cs_reinf_layer.py
bmcs_cross_section/cs_design/cs_shape.py
bmcs_cross_section/matmod/__init__.py
bmcs_cross_section/matmod/concrete.py
bmcs_cross_section/matmod/concrete_old.py
bmcs_cross_section/matmod/ec2.py
bmcs_cross_section/matmod/ec2_creep_shrinkage.py
bmcs_cross_section/matmod/matmod.py
bmcs_cross_section/matmod/reinforcement.py
bmcs_cross_section/matmod/sz_advanced.py
bmcs_cross_section/matmod/concrete/__init__.py
bmcs_cross_section/matmod/concrete/concrete_compression_ec2.py
bmcs_cross_section/matmod/concrete/concrete_compression_ec2_plateau.py
bmcs_cross_section/matmod/concrete/concrete_compression_pwl.py
bmcs_cross_section/matmod/concrete/concrete_matmod.py
bmcs_cross_section/matmod/concrete/concrete_tension_pwl.py
bmcs_cross_section/matmod/concrete/ec2.py
bmcs_cross_section/matmod/concrete/ec2_concrete_matmod.py
bmcs_cross_section/matmod/concrete/ec2_concrete_matmod_base.py
bmcs_cross_section/matmod/concrete/ec2_plateau_concrete_matmod.py
bmcs_cross_section/mkappa/__init__.py
bmcs_cross_section/mkappa/mkappa.py
bmcs_cross_section/mkappa/mkappa_pstudy.py
bmcs_cross_section/mkappa/mkappa_rho.py
bmcs_cross_section/mxn/__init__.py
bmcs_cross_section/mxn/constitutive_law.py
bmcs_cross_section/mxn/cross_section.py
bmcs_cross_section/mxn/cross_section_component.py
bmcs_cross_section/mxn/cross_section_state.py
bmcs_cross_section/mxn/ecb_calib.py
bmcs_cross_section/mxn/mxn_class_extension.py
bmcs_cross_section/mxn/mxn_class_extension_handler.py
bmcs_cross_section/mxn/mxn_diagram.py
bmcs_cross_section/mxn/mxn_tree_node.py
bmcs_cross_section-0.0.57a0.dist-info/METADATA
bmcs_cross_section-0.0.57a0.dist-info/WHEEL
bmcs_cross_section-0.0.57a0.dist-info/top_level.txt
bmcs_cross_section-0.0.57a0.dist-info/RECORD
