Metadata-Version: 2.1
Name: bmcs_cross_section
Version: 0.0.57a0
Summary: Models of brittle-concrete composite cross sections.
Home-page: https://github.com/bmcs-group/bmcs_cross_section
Author: BMCS-Group
Author-email: rostislav.chudoba@rwt-aachen.de
License: MIT
Classifier: License :: OSI Approved :: MIT License
Classifier: Programming Language :: Python
Classifier: Programming Language :: Python :: 3
Classifier: Programming Language :: Python :: 3.6
Classifier: Programming Language :: Python :: Implementation :: CPython
Classifier: Programming Language :: Python :: Implementation :: PyPy
Requires-Python: >=3.6.0
